janarthana_own_cli01/__init__.py
janarthana_own_cli01/cli.py
janarthana_own_cli01-0.1.0.dist-info/METADATA
janarthana_own_cli01-0.1.0.dist-info/WHEEL
janarthana_own_cli01-0.1.0.dist-info/top_level.txt
janarthana_own_cli01-0.1.0.dist-info/RECORD
