Metadata-Version: 2.1
Name: janarthana_own_cli01
Version: 0.1.0
Summary: A command-line interface for Jana
Home-page: https://github.com/yourusername/janarthana_own_cli
Author: Your Name
Author-email: janarthana.life@gmail.com
Classifier: Programming Language :: Python :: 3
Classifier: License :: OSI Approved :: MIT License
Classifier: Operating System :: OS Independent
Requires-Python: >=3.6
